bc4py_extension.cp37-win_amd64.pyd
bc4py_extension-0.1.7.dist-info/LICENSE
bc4py_extension-0.1.7.dist-info/METADATA
bc4py_extension-0.1.7.dist-info/WHEEL
bc4py_extension-0.1.7.dist-info/top_level.txt
bc4py_extension-0.1.7.dist-info/RECORD
