Metadata-Version: 2.1
Name: bc4py-extension
Version: 0.1.7
Summary: python extension for bc4py
Home-page: https://github.com/namuyan/bc4py_extension
License: MIT Licence
Platform: UNKNOWN
Classifier: License :: OSI Approved :: MIT License
Classifier: Programming Language :: Python :: 3
Classifier: Programming Language :: Rust
Requires-Dist: setuptools-rust (>=0.10.6)
